drf_multi_serializers/__init__.py
drf_multi_serializers/exceptions.py
drf_multi_serializers/mixins.py
drf_multi_serializers-1.4.0.dist-info/METADATA
drf_multi_serializers-1.4.0.dist-info/WHEEL
drf_multi_serializers-1.4.0.dist-info/licenses/LICENSE
drf_multi_serializers-1.4.0.dist-info/RECORD
