Metadata-Version: 2.4
Name: drf-multi-serializers
Version: 1.4.0
Summary: Handle multiple serializers for the same view in Django Rest Framework.
Project-URL: Homepage, https://github.com/stefanofusai/drf-multi-serializers
Project-URL: Repository, https://github.com/stefanofusai/drf-multi-serializers
Author-email: Stefano Fusai <stefanofusai@gmail.com>
Maintainer-email: Stefano Fusai <stefanofusai@gmail.com>
License-File: LICENSE
Requires-Python: >=3.12
Requires-Dist: djangorestframework<4.0.0,>=3.0.0
